wav2vec/WavDecoder.py
wav2vec/__init__.py
wav2vec/main.py
wav2vec/formatter/Formatter.py
wav2vec/formatter/__init__.py
wav2vec/formatter/formatters.py
wav2vec-1.1.0.dist-info/licenses/LICENSE.txt
wav2vec-1.1.0.dist-info/METADATA
wav2vec-1.1.0.dist-info/WHEEL
wav2vec-1.1.0.dist-info/entry_points.txt
wav2vec-1.1.0.dist-info/top_level.txt
wav2vec-1.1.0.dist-info/RECORD
