Metadata-Version: 2.4
Name: wav2vec
Version: 1.1.0
Summary: A Python package to convert waveform files (WAV or AIFF) to vector graphics (SVG, PostScript, or CVS)
Home-page: https://github.com/cristoper/wav2vec
Author: Chris Burkhardt
Author-email: dev@orangenoiseproduction.com
License: WTFPL
Keywords: audio graphics svg postscript data
Classifier: Development Status :: 4 - Beta
Classifier: Intended Audience :: Developers
Classifier: Topic :: Software Development :: Libraries :: Python Modules
Classifier: Programming Language :: Python :: 2.7
Classifier: Programming Language :: Python :: 3
Requires-Python: >=2.7
License-File: LICENSE.txt
Requires-Dist: standard-aifc
Requires-Dist: standard-chunk
Requires-Dist: standard-sndhdr
Dynamic: author
Dynamic: author-email
Dynamic: classifier
Dynamic: description
Dynamic: description-content-type
Dynamic: home-page
Dynamic: keywords
Dynamic: license
Dynamic: license-file
Dynamic: requires-dist
Dynamic: requires-python
Dynamic: summary
